hatchet/__init__.py
hatchet/node.py
hatchet/chopper.py
hatchet/graphframe.py
hatchet/version.py
hatchet/frame.py
hatchet/query.py
hatchet/graph.py
hatchet/cython_modules/libs/__init__.py
hatchet/cython_modules/libs/reader_modules.cpython-39-x86_64-linux-gnu.so
hatchet/cython_modules/libs/graphframe_modules.cpython-39-x86_64-linux-gnu.so
hatchet/external/__init__.py
hatchet/external/console.py
hatchet/tests/timemory_func.py
hatchet/tests/caliper.py
hatchet/tests/callgrind.py
hatchet/tests/executable.py
hatchet/tests/node.py
hatchet/tests/gprof.py
hatchet/tests/timemory_test.py
hatchet/tests/tau.py
hatchet/tests/dataframe_ops.py
hatchet/tests/hpctoolkit.py
hatchet/tests/omnitrace_test.py
hatchet/tests/pyinstrument.py
hatchet/tests/graph_literal.py
hatchet/tests/chopper.py
hatchet/tests/graphframe.py
hatchet/tests/conftest.py
hatchet/tests/logger.py
hatchet/tests/spotdb_test.py
hatchet/tests/cprofile.py
hatchet/tests/profiler.py
hatchet/tests/frame.py
hatchet/tests/scorep.py
hatchet/tests/graph_ops.py
hatchet/tests/query.py
hatchet/tests/graph.py
hatchet/readers/caliper_reader.py
hatchet/readers/__init__.py
hatchet/readers/perfetto_reader.py
hatchet/readers/cprofile_reader.py
hatchet/readers/scorep_reader.py
hatchet/readers/apex_reader.py
hatchet/readers/literal_reader.py
hatchet/readers/dataframe_reader.py
hatchet/readers/hpctoolkit_v4_reader.py
hatchet/readers/hdf5_reader.py
hatchet/readers/timemory_reader.py
hatchet/readers/tau_reader.py
hatchet/readers/hpctoolkit_reader.py
hatchet/readers/caliper_native_reader.py
hatchet/readers/gprof_dot_reader.py
hatchet/readers/spotdb_reader.py
hatchet/readers/pyinstrument_reader.py
hatchet/util/__init__.py
hatchet/util/executable.py
hatchet/util/readers.py
hatchet/util/deprecated.py
hatchet/util/logger.py
hatchet/util/config.py
hatchet/util/colormaps.py
hatchet/util/profiler.py
hatchet/util/dot.py
hatchet/util/timer.py
hatchet-1.4.1.dist-info/top_level.txt
hatchet-1.4.1.dist-info/WHEEL
hatchet-1.4.1.dist-info/RECORD
hatchet-1.4.1.dist-info/METADATA
hatchet-1.4.1.dist-info/NOTICE
hatchet-1.4.1.dist-info/LICENSE
